csc_440_salted_hash/__init__.py
csc_440_salted_hash/saltedHash.py
csc_440_salted_hash-0.3.dist-info/METADATA
csc_440_salted_hash-0.3.dist-info/RECORD
csc_440_salted_hash-0.3.dist-info/WHEEL
csc_440_salted_hash-0.3.dist-info/top_level.txt
