Metadata-Version: 2.1
Name: csc-440-salted-hash
Version: 0.3
Summary: Make and check salted hash passwords.
Home-page: UNKNOWN
Author: eboych
Author-email: UNKNOWN
License: UNKNOWN
Platform: UNKNOWN
